comedrivewithmeman/__init__.py
comedrivewithmeman/main.py
comedrivewithmeman-0.1.3.dist-info/METADATA
comedrivewithmeman-0.1.3.dist-info/WHEEL
comedrivewithmeman-0.1.3.dist-info/entry_points.txt
comedrivewithmeman-0.1.3.dist-info/top_level.txt
comedrivewithmeman-0.1.3.dist-info/RECORD
